{
  "title": "Elements",
  "description": [
    "Styles for html tags. MUST NOT contain styles for any classes, ids, or attributes. `Element` SHOULD use `bits` to construct rule sets."
  ],
  "sections": [
    {
      "key": "headings",
      "title": "Headings",
      "description": [
        "Part of the typography module. MUST use `$h1` - `$h6` variables."
      ],
      "file": "/src/scss/01_elements/_typography.scss",
      "display": true
    },
    {
      "key": "ap",
      "title": "Links & Paragraphs",
      "description": [
        "Part of the typogrpahy module. MUST use `$text_size` and `$text_line_height` variables."
      ],
      "file": "/src/scss/01_elements/_typography.scss",
      "display": true
    },
    {
      "key": "lists",
      "title": "Lists",
      "description": [
        "Lists module MUST use `$lists_font_size` and `$lists_line_height` variables. SHOULD lay foundational styles for `collection` lists."
      ],
      "file": "/src/scss/01_elements/_lists.scss",
      "display": true
    },
    {
      "key": "forms",
      "title": "Forms",
      "description": [
        "Forms module SHOULD lay foundational styles for forms `collections`."
      ],
      "file": "/src/scss/01_elements/_forms.scss",
      "display": true
    },
    {
      "key": "tables",
      "title": "Tables",
      "description": [
        "Tables module SHOULD lay foundational styles for tables `collections`."
      ],
      "file": "/src/scss/01_elements/_tables.scss",
      "display": true
    }
  ]
}
